milto/__init__.py
milto/base.py
milto/common.py
milto/etl.py
coingecko_milto-1.dist-info/LICENSE.txt
coingecko_milto-1.dist-info/METADATA
coingecko_milto-1.dist-info/WHEEL
coingecko_milto-1.dist-info/entry_points.txt
coingecko_milto-1.dist-info/top_level.txt
coingecko_milto-1.dist-info/RECORD
